interactivede/__init__.py
interactivede/_version.py
interactivede/install.json
interactivede/ide/__init__.py
interactivede/internal/__init__.py
interactivede/internal/dataframe/__init__.py
interactivede/internal/dataframe/dframe.py
interactivede-1.0.1.data/data/share/jupyter/labextensions/interactivede/package.json
interactivede-1.0.1.data/data/share/jupyter/labextensions/interactivede/static/282.a4b89d01150bfc1023ad.js
interactivede-1.0.1.data/data/share/jupyter/labextensions/interactivede/static/341.add2db8a792e0a57de80.js
interactivede-1.0.1.data/data/share/jupyter/labextensions/interactivede/static/519.681fb200eb8677022a34.js
interactivede-1.0.1.data/data/share/jupyter/labextensions/interactivede/static/519.681fb200eb8677022a34.js.LICENSE.txt
interactivede-1.0.1.data/data/share/jupyter/labextensions/interactivede/static/574.33d3db8a7a44ee9763c3.js
interactivede-1.0.1.data/data/share/jupyter/labextensions/interactivede/static/574.33d3db8a7a44ee9763c3.js.LICENSE.txt
interactivede-1.0.1.data/data/share/jupyter/labextensions/interactivede/static/653.f2c3e99d80a770e1b8b5.js
interactivede-1.0.1.data/data/share/jupyter/labextensions/interactivede/static/754.912aeaf8e21fe8c78f5c.js
interactivede-1.0.1.data/data/share/jupyter/labextensions/interactivede/static/754.912aeaf8e21fe8c78f5c.js.LICENSE.txt
interactivede-1.0.1.data/data/share/jupyter/labextensions/interactivede/static/remoteEntry.5dbfa0fea04d45eb2df0.js
interactivede-1.0.1.data/data/share/jupyter/labextensions/interactivede/static/style.js
interactivede-1.0.1.data/data/share/jupyter/labextensions/interactivede/static/third-party-licenses.json
interactivede-1.0.1.data/data/share/jupyter/labextensions/interactivede/install.json
interactivede-1.0.1.dist-info/METADATA
interactivede-1.0.1.dist-info/WHEEL
interactivede-1.0.1.dist-info/licenses/LICENSE
interactivede-1.0.1.dist-info/RECORD
